{
  "nodes": [
    {
      "parameters": {
        "operation": "create",
        "tableId": "execution_log",
        "fieldsUi": {
          "fieldValues": [
            {
              "fieldId": "user_phone",
              "fieldValue": "={{ $('setar_user').item.json.telefone }}"
            },
            {
              "fieldId": "user_id",
              "fieldValue": "={{ $('setar_user').item.json.id_user }}"
            },
            {
              "fieldId": "user_plan",
              "fieldValue": "premium"
            },
            {
              "fieldId": "action_type",
              "fieldValue": "={{ $json.parsed_output ? $json.parsed_output.acao : 'unknown' }}"
            },
            {
              "fieldId": "action_input",
              "fieldValue": "={{ $json.parsed_output && $json.parsed_output.tool ? JSON.stringify($json.parsed_output.tool) : null }}"
            },
            {
              "fieldId": "action_success",
              "fieldValue": true
            },
            {
              "fieldId": "source_workflow",
              "fieldValue": "premium"
            },
            {
              "fieldId": "event_type",
              "fieldValue": "action_executed"
            },
            {
              "fieldId": "status",
              "fieldValue": "completed"
            }
          ]
        }
      },
      "type": "n8n-nodes-base.supabase",
      "typeVersion": 1,
      "position": [1820, -700],
      "id": "log-action-orfa",
      "name": "Log: action (órfã)",
      "credentials": {
        "supabaseApi": {
          "id": "1ENA7UIm6ILehilJ",
          "name": "Supabase account"
        }
      },
      "continueOnFail": true
    }
  ],
  "connections": {}
}
